LICENSE
nrpylatex/.DS_Store
nrpylatex/__init__.py
nrpylatex/core/__init__.py
nrpylatex/core/generator.py
nrpylatex/core/parser.py
nrpylatex/core/scanner.py
nrpylatex/parse_latex.py
nrpylatex/tests/__init__.py
nrpylatex/tests/test_parse_latex.py
nrpylatex/utils/__init__.py
nrpylatex/utils/assertion.py
nrpylatex/utils/exceptions.py
nrpylatex/utils/functional.py
nrpylatex/utils/ipython.py
nrpylatex/utils/structures.py
nrpylatex-1.4.0.dist-info/LICENSE
nrpylatex-1.4.0.dist-info/METADATA
nrpylatex-1.4.0.dist-info/WHEEL
nrpylatex-1.4.0.dist-info/RECORD
