Metadata-Version: 2.1
Name: nrpylatex
Version: 1.4.0
Summary: LaTeX Interface to SymPy (CAS) for General Relativity
Home-page: https://github.com/nrpy/nrpylatex
License: BSD-2-Clause
Author: Ken Sible
Author-email: ksible@outlook.com
Requires-Python: >=2.7, !=3.0.*, !=3.1.*, !=3.2.*, !=3.3.*, !=3.4.*, !=3.5.*
Classifier: License :: OSI Approved :: BSD License
Classifier: Operating System :: OS Independent
Classifier: Programming Language :: Python
Classifier: Programming Language :: Python :: 2
Classifier: Programming Language :: Python :: 2.7
Classifier: Programming Language :: Python :: 3
Classifier: Programming Language :: Python :: 3.6
Classifier: Programming Language :: Python :: 3.7
Classifier: Programming Language :: Python :: 3.8
Classifier: Programming Language :: Python :: 3.9
Classifier: Programming Language :: Python :: 3.10
Classifier: Programming Language :: Python :: 3.11
Classifier: Programming Language :: Python :: 3.12
Classifier: Topic :: Scientific/Engineering
Classifier: Topic :: Scientific/Engineering :: Astronomy
Classifier: Topic :: Scientific/Engineering :: Mathematics
Classifier: Topic :: Scientific/Engineering :: Physics
Classifier: Topic :: Software Development :: Code Generators
Classifier: Topic :: Text Processing :: Markup :: LaTeX
Provides-Extra: jupyter
Requires-Dist: ipykernel (>=6.29.5,<7.0.0) ; (python_version >= "3.8") and (extra == "jupyter")
Requires-Dist: sympy (>=1.2,<2.0)
